pytest_mocktcp/__init__.py
pytest_mocktcp/framing.py
pytest_mocktcp/plugin.py
pytest_mocktcp-0.5.1.dist-info/LICENSE
pytest_mocktcp-0.5.1.dist-info/METADATA
pytest_mocktcp-0.5.1.dist-info/WHEEL
pytest_mocktcp-0.5.1.dist-info/entry_points.txt
pytest_mocktcp-0.5.1.dist-info/top_level.txt
pytest_mocktcp-0.5.1.dist-info/RECORD
