Metadata-Version: 2.1
Name: pytest-mocktcp
Version: 0.5.1
Summary: A pytest plugin for testing TCP clients
Author-email: Anders Lindstrom <anders@anderslindstrom.com>
License: MIT License        
Project-URL: Homepage, https://github.com/andersglindstrom/pytest-mocktcp.git
Classifier: Programming Language :: Python :: 3
Classifier: License :: OSI Approved :: MIT License
Classifier: Operating System :: OS Independent
Requires-Python: >=3.8
License-File: LICENSE
Requires-Dist: pytest
Requires-Dist: pytest-asyncio
Requires-Dist: pytest-mock
